{
    "base": {
        "detected": true,
        "finishFamily": "Acrylic",
        "colors": [
            {
                "hex": "#E8E3DA",
                "coverage": 70
            },
            {
                "hex": "#A7C24C",
                "coverage": 30
            }
        ],
        "handle": {
            "detected": true,
            "type": "bar",
            "finish": "chrome",
            "hex": "#C0C0C0"
        }
    },
    "wall": {
        "detected": true,
        "finishFamily": "Acrylic",
        "colors": [
            {
                "hex": "#A7C24C",
                "coverage": 65
            },
            {
                "hex": "#E8E3DA",
                "coverage": 35
            }
        ],
        "handle": {
            "detected": true,
            "type": "bar",
            "finish": "chrome",
            "hex": "#C0C0C0"
        }
    },
    "tall": {
        "detected": false,
        "finishFamily": "Unknown",
        "colors": [],
        "handle": {
            "detected": false,
            "type": "unknown",
            "finish": "unknown",
            "hex": null
        }
    },
    "loft": {
        "detected": true,
        "finishFamily": "Acrylic",
        "colors": [
            {
                "hex": "#A7C24C",
                "coverage": 90
            },
            {
                "hex": "#E8E3DA",
                "coverage": 10
            }
        ],
        "handle": {
            "detected": true,
            "type": "bar",
            "finish": "chrome",
            "hex": "#C0C0C0"
        }
    },
    "dado": {
        "detected": true,
        "finishFamily": "Tile",
        "colors": [
            {
                "hex": "#7C766E",
                "coverage": 100
            }
        ]
    },
    "floor": {
        "detected": false,
        "finishFamily": "Unknown",
        "colors": []
    },
    "ceilingLighting": {
        "detected": true,
        "type": "recessed_downlights",
        "count": 4,
        "layout": "linear",
        "colorTemperature": "neutral_white"
    }
}